changepoynt/__init__.py
changepoynt/algorithms/__init__.py
changepoynt/algorithms/base_algorithm.py
changepoynt/algorithms/baseline.py
changepoynt/algorithms/bocpd.py
changepoynt/algorithms/clasp.py
changepoynt/algorithms/esst.py
changepoynt/algorithms/floss.py
changepoynt/algorithms/fluss.py
changepoynt/algorithms/rulsif.py
changepoynt/algorithms/si.py
changepoynt/algorithms/sst.py
changepoynt/algorithms/torch_esst.py
changepoynt/algorithms/ulsif.py
changepoynt/utils/__init__.py
changepoynt/utils/densityratioestimation.py
changepoynt/utils/linalg.py
changepoynt/utils/normalization.py
changepoynt/visualization/__init__.py
changepoynt/visualization/score_plotting.py
changepoynt-0.1.1.dist-info/licenses/LICENSE
changepoynt-0.1.1.dist-info/METADATA
changepoynt-0.1.1.dist-info/WHEEL
changepoynt-0.1.1.dist-info/top_level.txt
changepoynt-0.1.1.dist-info/RECORD
