Metadata-Version: 2.4
Name: changepoynt
Version: 0.1.1
Summary: Efficient and readable change point detection package implemented in Python. (Singular Spectrum Transformation - SST, IKA-SST, ulSIF, RuLSIF, KLIEP, FLUSS, FLOSS, etc.)
Home-page: https://github.com/Lucew/changepoynt
Author: Lucas Weber
Author-email: Lucas Weber <weber-lucas@web.de>
License-Expression: BSD-2-Clause
Project-URL: Homepage, https://github.com/Lucew/changepoynt
Project-URL: Issues, https://github.com/Lucew/changepoynt/issues
Keywords: changepoint,times series,engineering,SST,change point detection,CPD
Classifier: Programming Language :: Python :: 3
Classifier: Operating System :: OS Independent
Classifier: Topic :: Scientific/Engineering
Requires-Python: >=3.8
License-File: LICENSE
Requires-Dist: numpy>=1.23.5
Requires-Dist: numba>=0.56.4
Requires-Dist: scipy>=1.10.1
Requires-Dist: fbpca>=1.0
Requires-Dist: matplotlib>=3.7.1
Requires-Dist: stumpy>=1.11.1
Requires-Dist: rocket-fft
Provides-Extra: test
Requires-Dist: pytest>=7.2.2; extra == "test"
Requires-Dist: numpy>=1.23.5; extra == "test"
Requires-Dist: numba>=0.56.4; extra == "test"
Requires-Dist: scipy>=1.10.1; extra == "test"
Requires-Dist: fbpca>=1.0; extra == "test"
Requires-Dist: stumpy>=1.11.1; extra == "test"
Requires-Dist: rocket-fft; extra == "test"
Provides-Extra: example
Requires-Dist: pytest>=7.2.2; extra == "example"
Requires-Dist: numpy>=1.23.5; extra == "example"
Requires-Dist: numba>=0.56.4; extra == "example"
Requires-Dist: scipy>=1.10.1; extra == "example"
Requires-Dist: seaborn>=0.12.2; extra == "example"
Requires-Dist: jupyter>=1.0.0; extra == "example"
Requires-Dist: fbpca>=1.0; extra == "example"
Requires-Dist: stumpy>=1.11.1; extra == "example"
Requires-Dist: rocket-fft; extra == "example"
Dynamic: author
Dynamic: home-page
Dynamic: license-file
